{
    "image-name": "C:\\Users\\User\\Desktop\\Robotics\\MyImageGroup\\new_data_set\\sub_data\\group_0\\000076.jpg",
    "width": 640,
    "height": 480,
    "boxes_canvas": [
        [
            606,
            353,
            654,
            496
        ],
        [
            640,
            355,
            767,
            421
        ],
        [
            517,
            320,
            554,
            352
        ],
        [
            503,
            343,
            571,
            424
        ],
        [
            663,
            349,
            694,
            379
        ],
        [
            633,
            386,
            760,
            431
        ],
        [
            531,
            263,
            601,
            352
        ],
        [
            465,
            296,
            497,
            388
        ],
        [
            424,
            437,
            551,
            476
        ],
        [
            304,
            356,
            439,
            414
        ],
        [
            423,
            415,
            461,
            451
        ],
        [
            484,
            492,
            531,
            554
        ],
        [
            155,
            358,
            294,
            438
        ],
        [
            156,
            403,
            322,
            586
        ]
    ],
    "attribute": [
        [
            3,
            22,
            9,
            0,
            0,
            0,
            0,
            0,
            0,
            0
        ],
        [
            27,
            24,
            34,
            37,
            0,
            0,
            0,
            0,
            0,
            0
        ],
        [
            3,
            10,
            0,
            0,
            0,
            0,
            0,
            0,
            0,
            0
        ],
        [
            37,
            27,
            0,
            0,
            0,
            0,
            0,
            0,
            0,
            0
        ],
        [
            3,
            10,
            0,
            0,
            0,
            0,
            0,
            0,
            0,
            0
        ],
        [
            24,
            27,
            35,
            0,
            0,
            0,
            0,
            0,
            0,
            0
        ],
        [
            24,
            27,
            34,
            3,
            0,
            0,
            0,
            0,
            0,
            0
        ],
        [
            9,
            25,
            0,
            0,
            0,
            0,
            0,
            0,
            0,
            0
        ],
        [
            15,
            27,
            0,
            0,
            0,
            0,
            0,
            0,
            0,
            0
        ],
        [
            3,
            35,
            27,
            0,
            0,
            0,
            0,
            0,
            0,
            0
        ],
        [
            3,
            11,
            0,
            0,
            0,
            0,
            0,
            0,
            0,
            0
        ],
        [
            3,
            10,
            0,
            0,
            0,
            0,
            0,
            0,
            0,
            0
        ],
        [
            3,
            24,
            35,
            0,
            0,
            0,
            0,
            0,
            0,
            0
        ],
        [
            27,
            0,
            0,
            0,
            0,
            0,
            0,
            0,
            0,
            0
        ]
    ],
    "boxes_1024": [
        [
            555,
            493,
            55,
            166
        ],
        [
            640,
            451,
            147,
            76
        ],
        [
            445,
            390,
            43,
            37
        ],
        [
            446,
            446,
            79,
            94
        ],
        [
            611,
            423,
            36,
            34
        ],
        [
            632,
            475,
            147,
            52
        ],
        [
            480,
            357,
            81,
            103
        ],
        [
            381,
            397,
            37,
            107
        ],
        [
            389,
            531,
            147,
            45
        ],
        [
            254,
            448,
            157,
            67
        ],
        [
            336,
            503,
            44,
            41
        ],
        [
            412,
            608,
            54,
            72
        ],
        [
            83,
            463,
            161,
            93
        ],
        [
            100,
            575,
            193,
            212
        ]
    ],
    "boxes_512": [
        [
            277,
            246,
            27,
            83
        ],
        [
            320,
            225,
            73,
            38
        ],
        [
            222,
            195,
            21,
            18
        ],
        [
            223,
            223,
            39,
            47
        ],
        [
            305,
            211,
            18,
            17
        ],
        [
            316,
            237,
            73,
            26
        ],
        [
            240,
            178,
            40,
            51
        ],
        [
            190,
            198,
            18,
            53
        ],
        [
            194,
            265,
            73,
            22
        ],
        [
            127,
            224,
            78,
            33
        ],
        [
            168,
            251,
            22,
            20
        ],
        [
            206,
            304,
            27,
            36
        ],
        [
            41,
            231,
            80,
            46
        ],
        [
            50,
            287,
            96,
            106
        ]
    ],
    "labels": [
        2,
        1,
        4,
        3,
        4,
        1,
        1,
        2,
        6,
        1,
        4,
        4,
        1,
        3
    ],
    "relationships": [
        [
            2,
            3
        ],
        [
            3,
            2
        ],
        [
            5,
            1
        ],
        [
            1,
            5
        ],
        [
            4,
            1
        ],
        [
            1,
            4
        ],
        [
            8,
            0
        ],
        [
            0,
            8
        ],
        [
            9,
            7
        ],
        [
            7,
            9
        ],
        [
            8,
            10
        ],
        [
            10,
            8
        ],
        [
            5,
            0
        ],
        [
            0,
            5
        ],
        [
            7,
            3
        ],
        [
            7,
            2
        ],
        [
            2,
            7
        ],
        [
            1,
            0
        ],
        [
            6,
            3
        ],
        [
            6,
            2
        ],
        [
            3,
            6
        ],
        [
            2,
            6
        ],
        [
            0,
            1
        ],
        [
            13,
            12
        ],
        [
            12,
            13
        ],
        [
            4,
            0
        ],
        [
            0,
            4
        ]
    ],
    "predicates": [
        10,
        17,
        17,
        10,
        10,
        17,
        9,
        9,
        9,
        9,
        6,
        2,
        2,
        6,
        9,
        9,
        9,
        2,
        2,
        2,
        6,
        6,
        6,
        17,
        10,
        9,
        9
    ]
}