{
    "image-name": "D:\\Working\\Research-with-Dr-Peng\\Annotation-Tool-For-SGG-Dataset\\sub_data\\sub_data\\group_2\\000275.jpg",
    "width": 640,
    "height": 480,
    "boxes_canvas": [
        [
            378,
            261,
            428,
            273
        ],
        [
            388,
            269,
            431,
            305
        ],
        [
            441,
            277,
            492,
            291
        ],
        [
            465,
            287,
            479,
            296
        ],
        [
            476,
            293,
            499,
            301
        ],
        [
            459,
            294,
            475,
            308
        ],
        [
            502,
            259,
            520,
            306
        ],
        [
            497,
            265,
            523,
            295
        ],
        [
            496,
            251,
            509,
            279
        ],
        [
            538,
            239,
            569,
            282
        ],
        [
            548,
            277,
            594,
            296
        ],
        [
            536,
            286,
            597,
            299
        ],
        [
            556,
            270,
            569,
            283
        ]
    ],
    "attribute": [
        [
            27,
            3,
            24,
            0,
            0,
            0,
            0,
            0,
            0,
            0
        ],
        [
            10,
            24,
            0,
            0,
            0,
            0,
            0,
            0,
            0,
            0
        ],
        [
            27,
            3,
            24,
            0,
            0,
            0,
            0,
            0,
            0,
            0
        ],
        [
            3,
            9,
            11,
            30,
            31,
            28,
            0,
            0,
            0,
            0
        ],
        [
            25,
            15,
            0,
            0,
            0,
            0,
            0,
            0,
            0,
            0
        ],
        [
            3,
            10,
            31,
            30,
            0,
            0,
            0,
            0,
            0,
            0
        ],
        [
            3,
            22,
            28,
            9,
            0,
            0,
            0,
            0,
            0,
            0
        ],
        [
            37,
            31,
            2,
            10,
            0,
            0,
            0,
            0,
            0,
            0
        ],
        [
            25,
            9,
            28,
            0,
            0,
            0,
            0,
            0,
            0,
            0
        ],
        [
            3,
            27,
            24,
            0,
            0,
            0,
            0,
            0,
            0,
            0
        ],
        [
            37,
            27,
            34,
            24,
            0,
            0,
            0,
            0,
            0,
            0
        ],
        [
            27,
            24,
            0,
            0,
            0,
            0,
            0,
            0,
            0,
            0
        ],
        [
            3,
            10,
            30,
            31,
            0,
            0,
            0,
            0,
            0,
            0
        ]
    ],
    "boxes_1024": [
        [
            290,
            310,
            58,
            13
        ],
        [
            298,
            333,
            50,
            41
        ],
        [
            364,
            330,
            59,
            16
        ],
        [
            371,
            339,
            16,
            10
        ],
        [
            389,
            345,
            26,
            9
        ],
        [
            365,
            350,
            18,
            16
        ],
        [
            416,
            328,
            20,
            54
        ],
        [
            415,
            325,
            30,
            34
        ],
        [
            406,
            308,
            15,
            32
        ],
        [
            466,
            303,
            36,
            50
        ],
        [
            486,
            333,
            53,
            22
        ],
        [
            481,
            340,
            70,
            15
        ],
        [
            476,
            321,
            15,
            15
        ]
    ],
    "boxes_512": [
        [
            145,
            155,
            29,
            6
        ],
        [
            149,
            166,
            25,
            20
        ],
        [
            182,
            165,
            29,
            8
        ],
        [
            185,
            169,
            8,
            5
        ],
        [
            194,
            172,
            13,
            4
        ],
        [
            182,
            175,
            9,
            8
        ],
        [
            208,
            164,
            10,
            27
        ],
        [
            207,
            162,
            15,
            17
        ],
        [
            203,
            154,
            7,
            16
        ],
        [
            233,
            151,
            18,
            25
        ],
        [
            243,
            166,
            26,
            11
        ],
        [
            240,
            170,
            35,
            7
        ],
        [
            238,
            160,
            7,
            7
        ]
    ],
    "labels": [
        1,
        3,
        1,
        4,
        6,
        4,
        2,
        4,
        2,
        1,
        1,
        1,
        4
    ],
    "relationships": [
        [
            0,
            1
        ],
        [
            2,
            1
        ],
        [
            3,
            2
        ],
        [
            3,
            1
        ],
        [
            5,
            2
        ],
        [
            5,
            3
        ],
        [
            2,
            7
        ],
        [
            3,
            7
        ],
        [
            4,
            7
        ],
        [
            6,
            7
        ],
        [
            6,
            5
        ],
        [
            7,
            8
        ],
        [
            2,
            8
        ],
        [
            9,
            8
        ],
        [
            9,
            7
        ],
        [
            10,
            11
        ],
        [
            11,
            6
        ],
        [
            11,
            9
        ],
        [
            12,
            10
        ],
        [
            5,
            6
        ],
        [
            11,
            7
        ]
    ],
    "predicates": [
        10,
        16,
        6,
        16,
        6,
        6,
        15,
        15,
        15,
        6,
        16,
        6,
        15,
        16,
        16,
        10,
        16,
        6,
        10,
        15,
        16
    ]
}