{
    "image-name": "C:\\Users\\24840360\\OneDrive - MMU\\Downloads\\sub_data\\sub_data\\group_7\\000756.jpg",
    "width": 640,
    "height": 480,
    "boxes_canvas": [
        [
            159,
            451,
            207,
            487
        ],
        [
            193,
            360,
            244,
            444
        ],
        [
            153,
            364,
            265,
            410
        ],
        [
            174,
            368,
            196,
            390
        ]
    ],
    "attribute": [
        [
            3,
            0,
            0,
            0,
            0,
            0,
            0,
            0,
            0,
            0
        ],
        [
            3,
            0,
            0,
            0,
            0,
            0,
            0,
            0,
            0,
            0
        ],
        [
            2,
            37,
            0,
            0,
            0,
            0,
            0,
            0,
            0,
            0
        ],
        [
            3,
            0,
            0,
            0,
            0,
            0,
            0,
            0,
            0,
            0
        ]
    ],
    "boxes_1024": [
        [
            34,
            545,
            55,
            41
        ],
        [
            76,
            467,
            59,
            97
        ],
        [
            65,
            450,
            130,
            53
        ],
        [
            37,
            441,
            25,
            25
        ]
    ],
    "boxes_512": [
        [
            17,
            272,
            27,
            20
        ],
        [
            38,
            233,
            29,
            48
        ],
        [
            32,
            225,
            65,
            26
        ],
        [
            18,
            220,
            12,
            12
        ]
    ],
    "labels": [
        4,
        2,
        1,
        4
    ],
    "relationships": [
        [
            3,
            2
        ],
        [
            2,
            1
        ],
        [
            1,
            0
        ],
        [
            0,
            1
        ]
    ],
    "predicates": [
        10,
        2,
        16,
        15
    ]
}